[
  {
    "full_name": "caomingkai/Front-End-Common-Problems",
    "stargazers_count": 38,
    "open_issues_count": 0,
    "forks_count": 13
  },
  {
    "full_name": "yangshun/front-end-interview-handbook",
    "stargazers_count": 36167,
    "open_issues_count": 13,
    "forks_count": 5273
  },
  {
    "full_name": "h5bp/Front-end-Developer-Interview-Questions",
    "stargazers_count": 55967,
    "open_issues_count": 7,
    "forks_count": 10729
  },
  {
    "full_name": "hxu296/leetcode-company-wise-problems-2022",
    "stargazers_count": 1506,
    "open_issues_count": 2,
    "forks_count": 450
  },
  {
    "full_name": "airbnb/swift",
    "stargazers_count": 1766,
    "open_issues_count": 0,
    "forks_count": 272
  },
  {
    "full_name": "airbnb/javascript",
    "stargazers_count": 129668,
    "open_issues_count": 149,
    "forks_count": 24668
  },
  {
    "full_name": "TheAlgorithms/Python",
    "stargazers_count": 149938,
    "open_issues_count": 111,
    "forks_count": 38531
  }
]